atomica_mcp/__main__.py
atomica_mcp/dataset.py
atomica_mcp/py.typed
atomica_mcp/server.py
atomica_mcp/upload_to_hf.py
atomica_mcp/mining/__init__.py
atomica_mcp/mining/cli.py
atomica_mcp/mining/pdb_metadata.py
atomica_mcp/preprocessing/__init__.py
atomica_mcp/preprocessing/download_dataset.py
atomica_mcp/preprocessing/pdb_utils.py
atomica_mcp/preprocessing/resolve_protein_names.py
atomica_mcp/preprocessing/resolve_proteins.py
atomica_mcp/preprocessing/sifts/__init__.py
atomica_mcp/preprocessing/sifts/download.py
atomica_mcp/preprocessing/sifts/utils.py
atomica_mcp-0.1.5.dist-info/METADATA
atomica_mcp-0.1.5.dist-info/WHEEL
atomica_mcp-0.1.5.dist-info/entry_points.txt
atomica_mcp-0.1.5.dist-info/licenses/LICENSE
atomica_mcp-0.1.5.dist-info/RECORD
