Metadata-Version: 2.4
Name: atomica-mcp
Version: 0.1.5
Summary: MCP server for PDB structure queries and protein resolution using AnAge database
Author-email: antonkulaga <antonkulaga@gmail.com>
License-File: LICENSE
Requires-Python: >=3.11
Requires-Dist: biotite>=1.5.0
Requires-Dist: eliot>=1.17.5
Requires-Dist: fastmcp>=2.12.5
Requires-Dist: fsspec>=2025.9.0
Requires-Dist: huggingface-hub>=0.35.3
Requires-Dist: numpy>=2.3.4
Requires-Dist: polars>=1.34.0
Requires-Dist: pycomfort>=0.0.18
Requires-Dist: requests>=2.32.5
Requires-Dist: rich>=13.9.0
Requires-Dist: tenacity>=9.1.2
Requires-Dist: typer>=0.20.0
Requires-Dist: urllib3>=2.5.0
